CHANGES
LICENSE
README.txt
TODO.txt
bootstrap.py
buildout.cfg
setup.cfg
setup.py
IngeniSkel.egg-info/PKG-INFO
IngeniSkel.egg-info/SOURCES.txt
IngeniSkel.egg-info/dependency_links.txt
IngeniSkel.egg-info/entry_points.txt
IngeniSkel.egg-info/not-zip-safe
IngeniSkel.egg-info/requires.txt
IngeniSkel.egg-info/top_level.txt
docs/iw_plone_project.txt
ez_setup/README.txt
ez_setup/__init__.py
ingeniskel/__init__.py
ingeniskel/templates/iw_plone_project/README.txt
ingeniskel/templates/iw_plone_project/base.cfg_tmpl
ingeniskel/templates/iw_plone_project/dev.cfg_tmpl
ingeniskel/templates/iw_plone_project/prod.cfg_tmpl
ingeniskel/templates/iw_plone_project/docs/Makefile
ingeniskel/templates/iw_plone_project/docs/source/conf.py_tmpl
ingeniskel/templates/iw_plone_project/docs/source/index.txt_tmpl
ingeniskel/templates/iw_plone_project/docs/source/installation.txt_tmpl
ingeniskel/templates/iw_plone_project/docs/source/iw_logo.png
ingeniskel/templates/iw_plone_project/docs/source/options.tex
ingeniskel/templates/iw_plone_project/docs/source/_static/ingeniweb.css
ingeniskel/templates/iw_plone_project/docs/source/_templates/layout.html
ingeniskel/templates/iw_plone_project/docs/source/_templates/modindex.html
ingeniskel/templates/iw_plone_project/docs/source/_templates/search.html
ingeniskel/templates/iw_plone_project/downloads/README.txt
ingeniskel/tests/__init__.py
ingeniskel/tests/src/configure.zcml
ingeniskel/tests/src/configure2.zcml
ingeniskel/tests/waited/configure2.zcml
tests/__init__.py
tests/test_ingeniskeldocs.py