Metadata-Version: 1.0
Name: IngeniSkel
Version: 0.3.3
Summary: A collection of skeletons for quickstarting projects with Ingeniweb products.
Home-page: http://ingeniweb.svn.sourceforge.net/svnroot/ingeniweb/IngeniSkel
Author: Ingeniweb
Author-email: support@ingeniweb.com
License: UNKNOWN
Keywords: web zope command-line skeleton project
Platform: UNKNOWN
Classifier: Development Status :: 3 - Alpha
Classifier: Framework :: Zope2
Classifier: Framework :: Zope3
Classifier: Intended Audience :: Developers
Classifier: License :: OSI Approved :: GNU General Public License (GPL)
Classifier: Programming Language :: Python
Classifier: Topic :: Internet :: WWW/HTTP
Classifier: Topic :: Internet :: WWW/HTTP :: Dynamic Content
Classifier: Topic :: Software Development :: Libraries :: Python Modules
